Metadata-Version: 2.1
Name: APIFredTorVergata
Version: 0.1.0
Summary: Download e analisi dati tramite API Fred 
Home-page: UNKNOWN
Author: Luca Fiscariello
Author-email: <lucafiscariello@gmail.com>
License: UNKNOWN
Keywords: API,Fred,Database,Download
Platform: UNKNOWN
Classifier: Development Status :: 1 - Planning
Classifier: Intended Audience :: Developers
Classifier: Programming Language :: Python :: 3
Classifier: Operating System :: Unix
Classifier: Operating System :: MacOS :: MacOS X
Classifier: Operating System :: Microsoft :: Windows
